aigarmic/__init__.py
aigarmic/_img_utils.py
aigarmic/_nn_design.py
aigarmic/clean_up_annotations.py
aigarmic/file_handlers.py
aigarmic/main.py
aigarmic/manual_annotator.py
aigarmic/model.py
aigarmic/model_performance.py
aigarmic/plate.py
aigarmic/process_plate_image.py
aigarmic/rename_images.py
aigarmic/train.py
aigarmic/train_modular.py
aigarmic-1.1.1.dist-info/LICENSE
aigarmic-1.1.1.dist-info/METADATA
aigarmic-1.1.1.dist-info/WHEEL
aigarmic-1.1.1.dist-info/entry_points.txt
aigarmic-1.1.1.dist-info/RECORD
