Metadata-Version: 2.1
Name: aigarmic
Version: 1.1.1
Summary: Machine-learning assisted agar dilution MIC
License: GPL-3.0
Author: Alessandro Gerada
Requires-Python: >=3.9,<3.11
Classifier: License :: OSI Approved :: GNU General Public License v3 (GPLv3)
Classifier: Programming Language :: Python :: 3
Classifier: Programming Language :: Python :: 3.9
Classifier: Programming Language :: Python :: 3.10
Requires-Dist: imutils (>=0.5)
Requires-Dist: matplotlib (>=3.6)
Requires-Dist: numpy (>=1.26)
Requires-Dist: opencv-python (>=4.9)
Requires-Dist: pytest (>=8.1)
Requires-Dist: scikit-learn (>=1.4)
Requires-Dist: sphinx (>=7.2)
Requires-Dist: sphinx-argparse (>=0.4.0,<0.5.0)
Requires-Dist: tensorflow (==2.15) ; platform_machine != "arm64"
Requires-Dist: tensorflow-macos (==2.15) ; platform_system == "Darwin" and platform_machine == "arm64"
